LICENSE
costreduce/__init__.py
costreduce/core/__init__.py
costreduce/core/analyze.py
costreduce/core/providers/__init__.py
costreduce/core/providers/aws.py
costreduce/core/services/__init__.py
costreduce/core/services/aws/__init__.py
costreduce/core/services/aws/cloudwatch.py
costreduce/core/services/aws/ec2.py
costreduce/core/services/aws/s3.py
costreduce/main.py
costreduce/utils/format.py
costreduce-0.0.8.dist-info/entry_points.txt
costreduce-0.0.8.dist-info/LICENSE
costreduce-0.0.8.dist-info/WHEEL
costreduce-0.0.8.dist-info/METADATA
costreduce-0.0.8.dist-info/RECORD
