Metadata-Version: 2.1
Name: costreduce
Version: 0.0.8
Summary: 
License: AGPL-3.0
Author: Maxence Maireaux
Author-email: maxence@maireaux.fr
Requires-Python: >=3.8,<4.0
Classifier: License :: OSI Approved :: GNU Affero General Public License v3
Classifier: Programming Language :: Python :: 3
Classifier: Programming Language :: Python :: 3.8
Requires-Dist: boto3 (>=1.13.6)
Requires-Dist: click (>=7.1.2)
Requires-Dist: click-log (>=0.3.2)
Requires-Dist: python-dotenv (>=0.13.0)
Requires-Dist: texttable (>=1.6.2)
